django_reactjs-0.4.2.dist-info/DESCRIPTION.rst
django_reactjs-0.4.2.dist-info/METADATA
django_reactjs-0.4.2.dist-info/RECORD
django_reactjs-0.4.2.dist-info/WHEEL
django_reactjs-0.4.2.dist-info/metadata.json
django_reactjs-0.4.2.dist-info/top_level.txt
reactjs/__init__.py
reactjs/apps.py
reactjs/conf.py
reactjs/models.py
reactjs/version.py
reactjs/static/reactjs/react-15.3.2.js
reactjs/static/reactjs/react-15.3.2.min.js
reactjs/static/reactjs/react-dom-15.3.2.js
reactjs/static/reactjs/react-dom-15.3.2.min.js
reactjs/static/reactjs/react-dom-server-15.3.2.js
reactjs/static/reactjs/react-dom-server-15.3.2.min.js
reactjs/static/reactjs/react-with-addons-15.3.2.js
reactjs/static/reactjs/react-with-addons-15.3.2.min.js
reactjs/templatetags/__init__.py
reactjs/templatetags/reactjs.py
